{
    "scope":  "Repository documentation audit inventory. Excludes documents/ prompt inputs, build outputs, dependency folders, .git internals, and local tmp folders.",
    "generated_on":  "2026-05-08",
    "total_artifacts":  129,
    "artifacts":  [
                      {
                          "path":  ".github/PULL_REQUEST_TEMPLATE/fdp-enablement-config-change.md",
                          "type":  "project",
                          "status":  "current-source-of-truth"
                      },
                      {
                          "path":  "deployment/service-identity/mtls/README.md",
                          "type":  "project",
                          "status":  "current-source-of-truth"
                      },
                      {
                          "path":  "deployment/service-identity/README.md",
                          "type":  "project",
                          "status":  "current-source-of-truth"
                      },
                      {
                          "path":  "docs/adr/fdp-29-evidence-gated-finalize.md",
                          "type":  "architecture",
                          "status":  "historical-or-template"
                      },
                      {
                          "path":  "docs/adr/fdp-36-real-chaos-enable-readiness.md",
                          "type":  "architecture",
                          "status":  "historical-or-template"
                      },
                      {
                          "path":  "docs/adr/fdp-37-production-image-chaos-enable-gate.md",
                          "type":  "architecture",
                          "status":  "historical-or-template"
                      },
                      {
                          "path":  "docs/adr/fdp-38-live-runtime-checkpoint-fixture-proof.md",
                          "type":  "architecture",
                          "status":  "historical-or-template"
                      },
                      {
                          "path":  "docs/adr/fdp-39-release-artifact-separation-governance.md",
                          "type":  "architecture",
                          "status":  "historical-or-template"
                      },
                      {
                          "path":  "docs/adr/fdp-40-platform-release-controls-signed-provenance-readiness.md",
                          "type":  "architecture",
                          "status":  "historical-or-template"
                      },
                      {
                          "path":  "docs/api/api-error-contract.md",
                          "type":  "api",
                          "status":  "current-source-of-truth"
                      },
                      {
                          "path":  "docs/api/api-surface-v1.md",
                          "type":  "api",
                          "status":  "current-source-of-truth"
                      },
                      {
                          "path":  "docs/api/fdp-29-api-response-contract.md",
                          "type":  "api",
                          "status":  "historical-or-template"
                      },
                      {
                          "path":  "docs/api/openapi-safety-audit.json",
                          "type":  "api",
                          "status":  "current-source-of-truth"
                      },
                      {
                          "path":  "docs/api/openapi-safety-audit.md",
                          "type":  "api",
                          "status":  "current-source-of-truth"
                      },
                      {
                          "path":  "docs/api/public-api-semantics.md",
                          "type":  "api",
                          "status":  "current-source-of-truth"
                      },
                      {
                          "path":  "docs/api/status-truth-table.md",
                          "type":  "api",
                          "status":  "current-source-of-truth"
                      },
                      {
                          "path":  "docs/architecture/alert-service-failure-windows.md",
                          "type":  "architecture",
                          "status":  "current-source-of-truth"
                      },
                      {
                          "path":  "docs/architecture/alert-service-source-of-truth.md",
                          "type":  "architecture",
                          "status":  "current-source-of-truth"
                      },
                      {
                          "path":  "docs/architecture/alert-service-write-path-inventory.md",
                          "type":  "architecture",
                          "status":  "current-source-of-truth"
                      },
                      {
                          "path":  "docs/architecture/current-architecture.md",
                          "type":  "architecture",
                          "status":  "current-source-of-truth"
                      },
                      {
                          "path":  "docs/architecture/diagrams.md",
                          "type":  "architecture",
                          "status":  "current-source-of-truth"
                      },
                      {
                          "path":  "docs/architecture/fdp-29-compatibility-matrix.md",
                          "type":  "architecture",
                          "status":  "historical-or-template"
                      },
                      {
                          "path":  "docs/architecture/fdp-29-evidence-preconditions.md",
                          "type":  "architecture",
                          "status":  "historical-or-template"
                      },
                      {
                          "path":  "docs/architecture/fdp-29-failure-windows.md",
                          "type":  "architecture",
                          "status":  "historical-or-template"
                      },
                      {
                          "path":  "docs/architecture/fdp-29-idempotency-replay.md",
                          "type":  "architecture",
                          "status":  "historical-or-template"
                      },
                      {
                          "path":  "docs/architecture/fdp-29-migration-rollout.md",
                          "type":  "architecture",
                          "status":  "historical-or-template"
                      },
                      {
                          "path":  "docs/architecture/fdp-29-state-machine.md",
                          "type":  "architecture",
                          "status":  "historical-or-template"
                      },
                      {
                          "path":  "docs/architecture/fdp-34-safe-checkpoint-adoption.md",
                          "type":  "architecture",
                          "status":  "historical-or-template"
                      },
                      {
                          "path":  "docs/architecture/fdp-34-safe-checkpoints.md",
                          "type":  "architecture",
                          "status":  "historical-or-template"
                      },
                      {
                          "path":  "docs/architecture/fdp-35-production-readiness-chaos-recovery-proof.md",
                          "type":  "architecture",
                          "status":  "historical-or-template"
                      },
                      {
                          "path":  "docs/configuration/configuration-guide.md",
                          "type":  "configuration",
                          "status":  "current-source-of-truth"
                      },
                      {
                          "path":  "docs/deployment/alert-service-config-matrix.md",
                          "type":  "project",
                          "status":  "current-source-of-truth"
                      },
                      {
                          "path":  "docs/documentation-audit.md",
                          "type":  "project",
                          "status":  "current-source-of-truth"
                      },
                      {
                          "path":  "docs/documentation-cleanup-merge-gate.md",
                          "type":  "release-proof",
                          "status":  "current-source-of-truth"
                      },
                      {
                          "path":  "docs/documentation-inventory.json",
                          "type":  "project",
                          "status":  "current-source-of-truth"
                      },
                      {
                          "path":  "docs/documentation-inventory.md",
                          "type":  "project",
                          "status":  "current-source-of-truth"
                      },
                      {
                          "path":  "docs/documentation-naming-map.md",
                          "type":  "project",
                          "status":  "current-source-of-truth"
                      },
                      {
                          "path":  "docs/documentation-style-guide.md",
                          "type":  "project",
                          "status":  "current-source-of-truth"
                      },
                      {
                          "path":  "docs/fdp-25-regulated-mutation-commit.md",
                          "type":  "project",
                          "status":  "historical-or-template"
                      },
                      {
                          "path":  "docs/fdp-27-merge-gate.md",
                          "type":  "release-proof",
                          "status":  "historical-or-template"
                      },
                      {
                          "path":  "docs/fdp-28b-chaos-handoff.md",
                          "type":  "project",
                          "status":  "historical-or-template"
                      },
                      {
                          "path":  "docs/fdp-28-invariant-proof-report.md",
                          "type":  "release-proof",
                          "status":  "historical-or-template"
                      },
                      {
                          "path":  "docs/fdp-29-design-checklist.md",
                          "type":  "release-proof",
                          "status":  "historical-or-template"
                      },
                      {
                          "path":  "docs/fdp-29-evidence-gated-finalize-handoff.md",
                          "type":  "project",
                          "status":  "historical-or-template"
                      },
                      {
                          "path":  "docs/fdp-29-implementation-merge-gate.md",
                          "type":  "release-proof",
                          "status":  "historical-or-template"
                      },
                      {
                          "path":  "docs/fdp-30-executor-split.md",
                          "type":  "project",
                          "status":  "historical-or-template"
                      },
                      {
                          "path":  "docs/fdp-31-claim-replay-policy-extraction.md",
                          "type":  "project",
                          "status":  "historical-or-template"
                      },
                      {
                          "path":  "docs/fdp-32-lease-fencing-stale-worker-protection.md",
                          "type":  "project",
                          "status":  "historical-or-template"
                      },
                      {
                          "path":  "docs/fdp-32-merge-gate.md",
                          "type":  "release-proof",
                          "status":  "historical-or-template"
                      },
                      {
                          "path":  "docs/fdp-33-lease-renewal-operational-readiness.md",
                          "type":  "project",
                          "status":  "historical-or-template"
                      },
                      {
                          "path":  "docs/fdp-33-merge-gate.md",
                          "type":  "release-proof",
                          "status":  "historical-or-template"
                      },
                      {
                          "path":  "docs/fdp-34-merge-gate.md",
                          "type":  "release-proof",
                          "status":  "historical-or-template"
                      },
                      {
                          "path":  "docs/fdp-35-merge-gate.md",
                          "type":  "release-proof",
                          "status":  "historical-or-template"
                      },
                      {
                          "path":  "docs/fdp-36-enablement-decision-checklist.md",
                          "type":  "release-proof",
                          "status":  "historical-or-template"
                      },
                      {
                          "path":  "docs/fdp-36-merge-gate.md",
                          "type":  "release-proof",
                          "status":  "historical-or-template"
                      },
                      {
                          "path":  "docs/fdp-37-enablement-decision-checklist.md",
                          "type":  "release-proof",
                          "status":  "historical-or-template"
                      },
                      {
                          "path":  "docs/fdp-37-merge-gate.md",
                          "type":  "release-proof",
                          "status":  "historical-or-template"
                      },
                      {
                          "path":  "docs/fdp-38-merge-gate.md",
                          "type":  "release-proof",
                          "status":  "historical-or-template"
                      },
                      {
                          "path":  "docs/fdp-39-merge-gate.md",
                          "type":  "release-proof",
                          "status":  "historical-or-template"
                      },
                      {
                          "path":  "docs/fdp-40-merge-gate.md",
                          "type":  "release-proof",
                          "status":  "historical-or-template"
                      },
                      {
                          "path":  "docs/historical-fdp-documents.md",
                          "type":  "project",
                          "status":  "current-source-of-truth"
                      },
                      {
                          "path":  "docs/index.md",
                          "type":  "project",
                          "status":  "current-source-of-truth"
                      },
                      {
                          "path":  "docs/ml/ml-governance-drift-v1.md",
                          "type":  "ml",
                          "status":  "current-source-of-truth"
                      },
                      {
                          "path":  "docs/observability/alert-service-slo.md",
                          "type":  "observability",
                          "status":  "current-source-of-truth"
                      },
                      {
                          "path":  "docs/observability/fdp-33-lease-renewal-dashboard.md",
                          "type":  "observability",
                          "status":  "historical-or-template"
                      },
                      {
                          "path":  "docs/observability/fdp-35-regulated-mutation-alert-thresholds.md",
                          "type":  "observability",
                          "status":  "historical-or-template"
                      },
                      {
                          "path":  "docs/observability/fdp-35-regulated-mutation-dashboard-spec.md",
                          "type":  "observability",
                          "status":  "historical-or-template"
                      },
                      {
                          "path":  "docs/observability/operations-observability-v1.md",
                          "type":  "observability",
                          "status":  "current-source-of-truth"
                      },
                      {
                          "path":  "docs/observability/operations-observability-v2.md",
                          "type":  "observability",
                          "status":  "current-source-of-truth"
                      },
                      {
                          "path":  "docs/openapi/alert-service.openapi.yaml",
                          "type":  "api",
                          "status":  "current-source-of-truth"
                      },
                      {
                          "path":  "docs/openapi/ml-inference-service.openapi.yaml",
                          "type":  "api",
                          "status":  "current-source-of-truth"
                      },
                      {
                          "path":  "docs/operations/fdp-35-regulated-mutation-rollback-plan.md",
                          "type":  "project",
                          "status":  "historical-or-template"
                      },
                      {
                          "path":  "docs/ops/fdp-37-dashboard-and-alert-thresholds.md",
                          "type":  "observability",
                          "status":  "historical-or-template"
                      },
                      {
                          "path":  "docs/ops/fdp-37-rollback-validation-output-template.md",
                          "type":  "project",
                          "status":  "historical-or-template"
                      },
                      {
                          "path":  "docs/release/fdp-39-approval-and-rollback-matrix.md",
                          "type":  "release-proof",
                          "status":  "historical-or-template"
                      },
                      {
                          "path":  "docs/release/fdp-39-branch-readme.md",
                          "type":  "release-proof",
                          "status":  "historical-or-template"
                      },
                      {
                          "path":  "docs/release/fdp-39-enablement-governance.md",
                          "type":  "release-proof",
                          "status":  "historical-or-template"
                      },
                      {
                          "path":  "docs/release/fdp-39-final-regulated-mutation-proof-matrix.md",
                          "type":  "release-proof",
                          "status":  "historical-or-template"
                      },
                      {
                          "path":  "docs/release/fdp-39-fixture-dockerfile-allowlist.json",
                          "type":  "release-proof",
                          "status":  "historical-or-template"
                      },
                      {
                          "path":  "docs/release/fdp-39-release-artifact-separation-matrix.md",
                          "type":  "release-proof",
                          "status":  "historical-or-template"
                      },
                      {
                          "path":  "docs/release/fdp-40-attestation-readiness-template.json",
                          "type":  "release-proof",
                          "status":  "historical-or-template"
                      },
                      {
                          "path":  "docs/release/fdp-40-branch-protection-readiness.json",
                          "type":  "release-proof",
                          "status":  "historical-or-template"
                      },
                      {
                          "path":  "docs/release/fdp-40-branch-protection-readiness.md",
                          "type":  "release-proof",
                          "status":  "historical-or-template"
                      },
                      {
                          "path":  "docs/release/fdp-40-branch-readme.md",
                          "type":  "release-proof",
                          "status":  "historical-or-template"
                      },
                      {
                          "path":  "docs/release/fdp-40-cosign-verification-readiness.md",
                          "type":  "release-proof",
                          "status":  "historical-or-template"
                      },
                      {
                          "path":  "docs/release/fdp-40-deployment-environment-readiness.json",
                          "type":  "release-proof",
                          "status":  "historical-or-template"
                      },
                      {
                          "path":  "docs/release/fdp-40-deployment-environment-readiness.md",
                          "type":  "release-proof",
                          "status":  "historical-or-template"
                      },
                      {
                          "path":  "docs/release/fdp-40-environment-protection-gates.json",
                          "type":  "release-proof",
                          "status":  "historical-or-template"
                      },
                      {
                          "path":  "docs/release/fdp-40-environment-protection-gates.md",
                          "type":  "release-proof",
                          "status":  "historical-or-template"
                      },
                      {
                          "path":  "docs/release/fdp-40-external-platform-controls-matrix.json",
                          "type":  "release-proof",
                          "status":  "historical-or-template"
                      },
                      {
                          "path":  "docs/release/fdp-40-external-platform-controls-matrix.md",
                          "type":  "release-proof",
                          "status":  "historical-or-template"
                      },
                      {
                          "path":  "docs/release/fdp-40-fdp39-provenance-reference.json",
                          "type":  "release-proof",
                          "status":  "historical-or-template"
                      },
                      {
                          "path":  "docs/release/fdp-40-proof-artifact-schema.md",
                          "type":  "release-proof",
                          "status":  "historical-or-template"
                      },
                      {
                          "path":  "docs/release/fdp-40-registry-immutability-readiness.json",
                          "type":  "release-proof",
                          "status":  "historical-or-template"
                      },
                      {
                          "path":  "docs/release/fdp-40-registry-immutability-readiness.md",
                          "type":  "release-proof",
                          "status":  "historical-or-template"
                      },
                      {
                          "path":  "docs/release/fdp-40-registry-promotion-policy.json",
                          "type":  "release-proof",
                          "status":  "historical-or-template"
                      },
                      {
                          "path":  "docs/release/fdp-40-registry-promotion-policy.md",
                          "type":  "release-proof",
                          "status":  "historical-or-template"
                      },
                      {
                          "path":  "docs/release/fdp-40-release-manifest-template.yaml",
                          "type":  "release-proof",
                          "status":  "historical-or-template"
                      },
                      {
                          "path":  "docs/release/fdp-40-required-checks-matrix.json",
                          "type":  "release-proof",
                          "status":  "historical-or-template"
                      },
                      {
                          "path":  "docs/release/fdp-40-required-checks-matrix.md",
                          "type":  "release-proof",
                          "status":  "historical-or-template"
                      },
                      {
                          "path":  "docs/release/fdp-40-residual-platform-gaps.md",
                          "type":  "release-proof",
                          "status":  "historical-or-template"
                      },
                      {
                          "path":  "docs/release/fdp-40-sbom-readiness-policy.md",
                          "type":  "release-proof",
                          "status":  "historical-or-template"
                      },
                      {
                          "path":  "docs/release/fdp-40-sbom-readiness-template.json",
                          "type":  "release-proof",
                          "status":  "historical-or-template"
                      },
                      {
                          "path":  "docs/release/fdp-40-signed-provenance-policy.md",
                          "type":  "release-proof",
                          "status":  "historical-or-template"
                      },
                      {
                          "path":  "docs/release/fdp-40-single-release-owner-governance.json",
                          "type":  "release-proof",
                          "status":  "historical-or-template"
                      },
                      {
                          "path":  "docs/release/fdp-40-single-release-owner-governance.md",
                          "type":  "release-proof",
                          "status":  "historical-or-template"
                      },
                      {
                          "path":  "docs/release/fdp-40-unsupported-claims-matrix.md",
                          "type":  "release-proof",
                          "status":  "historical-or-template"
                      },
                      {
                          "path":  "docs/runbooks/alert-service-production-runbooks.md",
                          "type":  "runbook",
                          "status":  "current-source-of-truth"
                      },
                      {
                          "path":  "docs/runbooks/fdp-29-finalize-recovery-required.md",
                          "type":  "runbook",
                          "status":  "historical-or-template"
                      },
                      {
                          "path":  "docs/runbooks/fdp-29-local-audit-chain-contention.md",
                          "type":  "runbook",
                          "status":  "historical-or-template"
                      },
                      {
                          "path":  "docs/runbooks/fdp-33-lease-renewal-runbook.md",
                          "type":  "runbook",
                          "status":  "historical-or-template"
                      },
                      {
                          "path":  "docs/runbooks/fdp-34-safe-checkpoint-renewal-runbook.md",
                          "type":  "runbook",
                          "status":  "historical-or-template"
                      },
                      {
                          "path":  "docs/runbooks/fdp-35-regulated-mutation-recovery-drill.md",
                          "type":  "runbook",
                          "status":  "historical-or-template"
                      },
                      {
                          "path":  "docs/runbooks/fdp-35-regulated-mutation-recovery-drill-runbook.md",
                          "type":  "runbook",
                          "status":  "historical-or-template"
                      },
                      {
                          "path":  "docs/runbooks/fdp-36-real-chaos-recovery-drill-runbook.md",
                          "type":  "runbook",
                          "status":  "historical-or-template"
                      },
                      {
                          "path":  "docs/runbooks/index.md",
                          "type":  "runbook",
                          "status":  "current-source-of-truth"
                      },
                      {
                          "path":  "docs/security/security-foundation-v1.md",
                          "type":  "security",
                          "status":  "current-source-of-truth"
                      },
                      {
                          "path":  "docs/security/service-identity-fdp-17.md",
                          "type":  "security",
                          "status":  "current-source-of-truth"
                      },
                      {
                          "path":  "docs/security/service-identity-fdp-18.md",
                          "type":  "security",
                          "status":  "current-source-of-truth"
                      },
                      {
                          "path":  "docs/testing/fdp-29-test-plan.md",
                          "type":  "project",
                          "status":  "historical-or-template"
                      },
                      {
                          "path":  "docs/testing/fdp-35-e2e-and-chaos-test-plan.md",
                          "type":  "project",
                          "status":  "historical-or-template"
                      },
                      {
                          "path":  "docs/testing/fdp-35-regression-proof-matrix.md",
                          "type":  "release-proof",
                          "status":  "historical-or-template"
                      },
                      {
                          "path":  "docs/testing/fdp-36-final-proof-pack.md",
                          "type":  "release-proof",
                          "status":  "historical-or-template"
                      },
                      {
                          "path":  "docs/testing/fdp-36-real-chaos-proof-matrix.md",
                          "type":  "release-proof",
                          "status":  "historical-or-template"
                      },
                      {
                          "path":  "docs/testing/fdp-37-final-proof-pack.md",
                          "type":  "release-proof",
                          "status":  "historical-or-template"
                      },
                      {
                          "path":  "docs/testing/fdp-37-production-image-chaos-proof-matrix.md",
                          "type":  "release-proof",
                          "status":  "historical-or-template"
                      },
                      {
                          "path":  "docs/testing/fdp-38-final-proof-pack.md",
                          "type":  "release-proof",
                          "status":  "historical-or-template"
                      },
                      {
                          "path":  "docs/testing/fdp-38-live-runtime-checkpoint-proof-matrix.md",
                          "type":  "release-proof",
                          "status":  "historical-or-template"
                      },
                      {
                          "path":  "README.md",
                          "type":  "project",
                          "status":  "current-source-of-truth"
                      }
                  ]
}
